{
  "kind": "collectionType",
  "collectionName": "finish_options",
  "info": {
    "singularName": "finish-option",
    "pluralName": "finish-options",
    "displayName": "Finish Option"
  },
  "options": {
    "draftAndPublish": true
  },
  "pluginOptions": {},
  "attributes": {
    "name": {
      "type": "string"
    },
    "thumbnail": {
      "type": "media",
      "multiple": false,
      "allowedTypes": [
        "images",
        "files",
        "videos",
        "audios"
      ]
    }
  }
}
